wwdtm/__init__.py
wwdtm/validation.py
wwdtm/guest/__init__.py
wwdtm/guest/appearances.py
wwdtm/guest/guest.py
wwdtm/guest/utility.py
wwdtm/host/__init__.py
wwdtm/host/appearances.py
wwdtm/host/host.py
wwdtm/host/utility.py
wwdtm/location/__init__.py
wwdtm/location/location.py
wwdtm/location/recordings.py
wwdtm/location/utility.py
wwdtm/panelist/__init__.py
wwdtm/panelist/appearances.py
wwdtm/panelist/decimal_scores.py
wwdtm/panelist/panelist.py
wwdtm/panelist/scores.py
wwdtm/panelist/statistics.py
wwdtm/panelist/utility.py
wwdtm/pronoun/__init__.py
wwdtm/pronoun/pronouns.py
wwdtm/scorekeeper/__init__.py
wwdtm/scorekeeper/appearances.py
wwdtm/scorekeeper/scorekeeper.py
wwdtm/scorekeeper/utility.py
wwdtm/show/__init__.py
wwdtm/show/info.py
wwdtm/show/info_multiple.py
wwdtm/show/show.py
wwdtm/show/utility.py
wwdtm-2.21.1.dist-info/licenses/LICENSE
wwdtm-2.21.1.dist-info/METADATA
wwdtm-2.21.1.dist-info/WHEEL
wwdtm-2.21.1.dist-info/top_level.txt
wwdtm-2.21.1.dist-info/RECORD
