Metadata-Version: 2.4
Name: wwdtm
Version: 2.21.1
Summary: Library used to query data from copy of Wait Wait Stats Database.
Author-email: Linh Pham <dev@wwdt.me>
License-Expression: Apache-2.0
Project-URL: Documentation, https://docs.wwdt.me
Project-URL: Source Code, https://github.com/questionlp/wwdtm
Project-URL: Changes, https://docs.wwdt.me/latest/changes/
Project-URL: Stats Page, https://stats.wwdt.me
Project-URL: Mastodon, https://linh.social/@qlp
Classifier: Development Status :: 5 - Production/Stable
Classifier: Intended Audience :: Developers
Classifier: Programming Language :: Python :: 3
Classifier: Programming Language :: Python :: 3.12
Classifier: Programming Language :: Python :: 3.13
Classifier: Programming Language :: Python :: 3.14
Classifier: Topic :: Software Development :: Libraries
Requires-Python: >=3.12
License-File: LICENSE
Requires-Dist: mysql-connector-python==9.4.0
Requires-Dist: numpy==2.3.3
Requires-Dist: python-slugify==8.0.4
Requires-Dist: pytz==2025.2
Dynamic: license-file
